{"expireTime":9007200867915876000,"key":"83441cc290be5490975ef1d0a7631271","val":{"name":"IMAGE_PROCESSING","inputPaths":["C:/Users/Joshua Stamps/OneDrive/GitHubRepos/master-jstamps.dev/content/images/explore-code-github.jpg"],"outputDir":"C:/Users/Joshua Stamps/OneDrive/GitHubRepos/master-jstamps.dev/public/static/45957feaeb8d6a3a2e9812beeb721ed6","args":{"isLazy":false,"operations":[{"outputPath":"f836f\\explore-code-github.jpg","args":{"width":200,"cropFocus":17,"toFormat":"jpg","fit":"cover","background":"rgba(0,0,0,1)"}},{"outputPath":"2244e\\explore-code-github.jpg","args":{"width":400,"cropFocus":17,"toFormat":"jpg","fit":"cover","background":"rgba(0,0,0,1)"}},{"outputPath":"14b42\\explore-code-github.jpg","args":{"width":800,"cropFocus":17,"toFormat":"jpg","fit":"cover","background":"rgba(0,0,0,1)"}},{"outputPath":"47498\\explore-code-github.jpg","args":{"width":1200,"cropFocus":17,"toFormat":"jpg","fit":"cover","background":"rgba(0,0,0,1)"}},{"outputPath":"0e329\\explore-code-github.jpg","args":{"width":1600,"cropFocus":17,"toFormat":"jpg","fit":"cover","background":"rgba(0,0,0,1)"}},{"outputPath":"69755\\explore-code-github.jpg","args":{"width":2048,"cropFocus":17,"toFormat":"jpg","fit":"cover","background":"rgba(0,0,0,1)"}}],"pluginOptions":{"base64Width":20,"forceBase64Format":"","useMozJpeg":false,"stripMetadata":true,"lazyImageGeneration":true,"defaultQuality":50,"failOnError":true,"plugins":[]}}}}